{
  "categories": [
    {
      "id": "1",
      "title": "ГАЗ",
      "row": 1
    },
    {
      "id": "2",
      "title": "УАЗ",
      "row": 1
    },
    {
      "id": "3",
      "title": "ВАЗ",
      "row": 1
    },
    {
      "id": "4",
      "title": "КАМАЗ",
      "row": 1
    },
    {
      "id": "5",
      "title": "ПАЗ",
      "row": 1
    },
    {
      "id": "6",
      "title": "ЛиАЗ, НЕФАЗ",
      "row": 1
    },
    {
      "id": "7",
      "title": "Тракторные запчасти",
      "row": 2
    },
    {
      "id": "8",
      "title": "Hyundai",
      "row": 2
    },
    {
      "id": "9",
      "title": "KIA",
      "row": 2
    },
    {
      "id": "10",
      "title": "KGM",
      "row": 2
    },
    {
      "id": "11",
      "title": "Эксплуатационные жидкости",
      "row": 2
    },
    {
      "id": "12",
      "title": "Подшипники",
      "row": 2
    }
  ],
  "news": [
    {
      "id": "1",
      "title": "Открытие нового склада",
      "description": "Мы открыли новый склад в Иркутской области.",
      "date": "2026-01-10"
    },
    {
      "id": "2",
      "title": "Снижение цен на автозапчасти",
      "description": "Снижение цен на популярные позиции до 15%.",
      "date": "2026-01-15"
    }
  ],
  "contacts": [
    {
      "id": "1",
      "title": "Автомобили",
      "phone": "(391) 256-88-46",
      "email": "akgs@akgs.biz"
    },
    {
      "id": "2",
      "title": "Запчасти",
      "phone": "(391) 290-14-60",
      "email": "akgs@akgs.biz"
    },
    {
      "id": "3",
      "title": "Сервис",
      "phone": "(391) 290-38-28",
      "email": "akgs@akgs.biz"
    },
    {
      "id": "4",
      "title": "Отдел гарантии",
      "phone": "(391) 290-38-28",
      "email": "akgs@akgs.biz"
    },
    {
      "id": "5",
      "title": "Отдел снабжения",
      "phone": "(391) 244-91-29, 290-04-52",
      "email": "akgs@akgs.biz"
    },
    {
      "id": "6",
      "title": "Отдел маркетинга и рекламы",
      "phone": "(391) 290-14-55",
      "email": "akgs@akgs.biz"
    },
    {
      "id": "7",
      "title": "Юридический отдел",
      "phone": "(391) 256-03-60",
      "email": "akgs@akgs.biz"
    },
    {
      "id": "8",
      "title": "Отдел по работе с персоналом",
      "phone": "(391) 241-54-96",
      "email": "66002850@mail.ru"
    }
  ],
  "stores": [
    {
      "id": "1",
      "city": "Красноярск",
      "address": "ул. Мечникова, 50",
      "phone": "8-800-775-44-50 доб. 1",
      "email": "kras2@akgs.market",
      "work": "Пн - Пт 09:00 - 18:00, Сб, Вс выходной"
    },
    {
      "id": "2",
      "city": "Абакан",
      "address": "ул. Советская, 219",
      "phone": "8-800-355-41-24 доб. 12",
      "email": "abk2@akgs.market",
      "work": "Пн - Пт 08:30 - 19:00, Сб, Вс 08:30 - 16:00"
    },
    {
      "id": "3",
      "city": "Абакан",
      "address": "пр-т Дружбы Народов, 52",
      "phone": "8-800-355-41-24 доб. 11",
      "email": "abk1@akgs.market",
      "work": "Пн - Пт 08:30 - 19:00, Сб, Вс 08:30 - 16:00"
    },
    {
      "id": "4",
      "city": "Ачинск",
      "address": "ул. Дзержинского, 49",
      "phone": "8-800-355-41-24 доб. 2",
      "email": "ach@akgs.market",
      "work": "Пн - Пт 09:00 - 18:00, Сб 09:00 - 15:00, Вс 09:00 - 14:00"
    },
    {
      "id": "5",
      "city": "Берёзовка",
      "address": "ул. Дружбы, 26а/3",
      "phone": "8-800-775-44-50 доб. 1",
      "email": "berezka@akgs.biz",
      "work": "Пн - Пт 09:00 - 19:00, Сб 09:00 - 18:00, Вс 09:00 - 16:00"
    },
    {
      "id": "6",
      "city": "Богучаны",
      "address": "ул. Ленина, 182",
      "phone": "8-800-355-41-24 доб. 3",
      "email": "bgn@akgs.market",
      "work": "Пн - Пт 08:30 - 18:00, Сб 08:30 - 16:00, Вс 08:30 - 14:00"
    },
    {
      "id": "7",
      "city": "Емельяново",
      "address": "2-х Борцов 21м",
      "phone": "8-800-775-44-50 доб. 1",
      "email": "emelyanovo@akgs.biz",
      "work": "Пн - Пт 09:00 - 19:00, Сб, Вс выходной"
    },
    {
      "id": "8",
      "city": "Канск",
      "address": "ул. 40 лет Октября, 88",
      "phone": "8-800-355-41-24 доб. 41",
      "email": "knk1@akgs.market",
      "work": "Пн - Пт 08:30 - 18:00, Сб, Вс 08:30 - 16:00"
    },
    {
      "id": "9",
      "city": "Канск",
      "address": "ул. Муромская, 13в",
      "phone": "8-800-355-41-24 доб. 43",
      "email": "knk3@akgs.market",
      "work": "Пн - Пт 08:30 - 18:00, Сб, Вс 08:30 - 14:00"
    },
    {
      "id": "10",
      "city": "Канск",
      "address": "ул. Эйдемана, 21 А",
      "phone": "8-800-355-41-24 доб. 42",
      "email": "knk2@akgs.market",
      "work": "Пн - Пт 08:30 - 18:00, Сб, Вс 08:30 - 16:00"
    },
    {
      "id": "11",
      "city": "Красноярск",
      "address": "ул. Цимлянская, 35 б",
      "phone": "8-800-775-44-50 доб. 1",
      "email": "35b@akgs.biz",
      "work": "Пн - Пт 09:00 - 18:00, Сб, Вс выходной"
    },
    {
      "id": "12",
      "city": "Красноярск",
      "address": "ул. Гайдашовка, 30",
      "phone": "8-800-775-44-50 доб. 1",
      "email": "ya50@akgs.biz",
      "work": "Пн - Пт 09:00 - 18:00, Сб, Вс выходной"
    },
    {
      "id": "13",
      "city": "Красноярск",
      "address": "ул. Глинки, 37а/1",
      "phone": "8-800-775-44-50 доб. 1",
      "email": "g37a@akgs.biz",
      "work": "Пн - Пт 09:00 - 18:00, Сб, Вс выходной"
    },
    {
      "id": "14",
      "city": "Красноярск",
      "address": "ул. Брянская, 137",
      "phone": "8-800-775-44-50 доб. 1",
      "email": "br137@akgs.biz",
      "work": "Пн - Пт 09:00 - 18:00, Сб, Вс выходной"
    },
    {
      "id": "15",
      "city": "Красноярск",
      "address": "ул. 60 лет Октября, 121а",
      "phone": "8-800-775-44-50 доб. 1",
      "email": "m75@akgs.biz",
      "work": "Пн - Пт 09:00 - 18:00, Сб, Вс выходной"
    },
    {
      "id": "16",
      "city": "Красноярск",
      "address": "Енисейский тракт, 85/1",
      "phone": "8-800-775-44-50 доб. 1",
      "email": "solar@akgs.biz",
      "work": "Пн - Пт 09:00 - 20:00, Сб 09:00 - 18:00, Вс 09:00 - 16:00"
    },
    {
      "id": "17",
      "city": "Лесосибирск",
      "address": "ул. Магистральная, 28",
      "phone": "8-800-355-41-24 доб. 5",
      "email": "les@akgs.market",
      "work": "Пн - Пт 08:30 - 19:00, Сб, Вс 08:30 - 18:00"
    },
    {
      "id": "18",
      "city": "Минусинск",
      "address": "ул. Суворова 21а",
      "phone": "8-800-355-41-24 доб. 6",
      "email": "min@akgs.market",
      "work": "Пн - Пт 08:30 - 18:00, Сб, Вс 08:30 - 15:00"
    }
  ],
  "vacancies": [
    {
      "id": "1",
      "title": "Продавец запасных частей",
      "city": "Абакан",
      "responsibilities": "Продажа, подбор, консультирование покупателей по наличию и ассортименту запасных частей в розничных магазинах.",
      "requirements": "Образование от средне-профессионального, знание номенклатуры запасных частей приветствуется, пользователь ПК, развитые коммуникативные навыки.",
      "conditions": "Официальное трудоустройство, соц.пакет.",
      "location": "г. Абакан, ул. Советская, 219",
      "contacts": {
        "name": "Бояров Евгений",
        "phone": "+7 (913) 542-54-61",
        "email": [
          "boyarovev@akgs.biz",
          "66002850@mail.ru"
        ]
      },
      "applicationLink": "/files/anketa-soiskatelya.pdf"
    },
    {
      "id": "2",
      "title": "Продавец запасных частей",
      "city": "Красноярск",
      "responsibilities": "Продажа, подбор, консультирование покупателей по наличию и ассортименту запасных частей в розничных магазинах.",
      "requirements": "Образование от средне-профессионального, знание номенклатуры запасных частей приветствуется, пользователь ПК, развитые коммуникативные навыки.",
      "conditions": "Официальное трудоустройство, соц.пакет, компенсация транспортных расходов.",
      "location": "г. Красноярск",
      "contacts": {
        "name": "Менеджер по персоналу",
        "phone": "2415-496",
        "email": [
          "66002850@mail.ru"
        ]
      },
      "applicationLink": "/files/anketa-soiskatelya.pdf"
    },
    {
      "id": "3",
      "title": "Кладовщик-комплектовщик",
      "city": "Красноярск",
      "responsibilities": "Работа на складе запасных частей (разгрузочно-погрузочные работы, перемещение товара).",
      "requirements": "Ответственность, внимательность, трудолюбие. Опыт работы не обязателен.",
      "conditions": "Оформление по ТК РФ, соц.пакет, обучение, оплата проезда, спецодежда, скидки, медосмотр за счет работодателя.",
      "location": "г. Красноярск, ул. Мечникова, 50",
      "contacts": {
        "name": "Менеджер по персоналу",
        "phone": "2415-496",
        "email": [
          "66002850@mail.ru"
        ]
      }
    }
  ],
  "cart": [],
  "orders": [
    {
      "id": "1",
      "number": "AKGS-0001",
      "date": "2026-01-20",
      "status": "В обработке",
      "total": 12490,
      "items": [
        {
          "title": "Фильтр масляный",
          "price": 990,
          "quantity": 2
        },
        {
          "title": "Колодки тормозные",
          "price": 5200,
          "quantity": 2
        }
      ]
    },
    {
      "id": "2",
      "number": "AKGS-0002",
      "date": "2026-01-10",
      "status": "Завершён",
      "total": 3490,
      "items": [
        {
          "title": "Свечи зажигания",
          "price": 3490,
          "quantity": 1
        }
      ]
    },
    {
      "id": "9e0d",
      "number": "AKGS-7500",
      "date": "2026-01-27T08:38:47.500Z",
      "status": "В обработке",
      "total": 3989,
      "items": [
        {
          "title": "Амортизатор передний",
          "price": 1499,
          "quantity": 1
        },
        {
          "title": "Тормозные колодки ГАЗ",
          "price": 2490,
          "quantity": 1
        }
      ]
    },
    {
      "id": "6631",
      "number": "AKGS-5004",
      "date": "2026-01-27T08:50:15.004Z",
      "status": "В обработке",
      "total": 2490,
      "items": [
        {
          "title": "Тормозные колодки ГАЗ",
          "price": 2490,
          "quantity": 1
        }
      ]
    }
  ],
  "products": [
    {
      "id": "1",
      "categoryId": "1",
      "title": "Амортизатор передний",
      "price": 1499,
      "oldPrice": 1699,
      "article": "AKG-00123",
      "brand": "KYB",
      "city": "Красноярск",
      "image": "/src/components/pages/images/product.jfif",
      "description": "Передний амортизатор для легковых автомобилей. Обеспечивает устойчивость и комфорт при движении.",
      "availability": true
    },
    {
      "id": "2",
      "categoryId": "1",
      "title": "Тормозные колодки ГАЗ",
      "price": 2490,
      "oldPrice": 2790,
      "article": "AKG-00234",
      "brand": "TRIALLI",
      "city": "Красноярск",
      "image": "/src/components/pages/images/product.jfif",
      "description": "Комплект передних тормозных колодок для автомобилей ГАЗ.",
      "availability": true
    },
    {
      "id": "3",
      "categoryId": "2",
      "title": "Масляный фильтр UAZ",
      "price": 690,
      "oldPrice": 750,
      "article": "AKG-00456",
      "brand": "MANN",
      "city": "Абакан",
      "image": "/src/components/pages/images/product.jfif",
      "description": "Масляный фильтр для дизельных двигателей УАЗ.",
      "availability": true
    },
    {
      "id": "4",
      "categoryId": "3",
      "title": "Свеча зажигания ВАЗ",
      "price": 320,
      "oldPrice": 390,
      "article": "AKG-00789",
      "brand": "NGK",
      "city": "Красноярск",
      "image": "/src/components/pages/images/product.jfif",
      "description": "Свеча зажигания для бензиновых двигателей ВАЗ.",
      "availability": true
    },
    {
      "id": "5",
      "categoryId": "4",
      "title": "Воздушный фильтр КАМАЗ",
      "price": 1890,
      "oldPrice": 1990,
      "article": "AKG-00999",
      "brand": "BIG FILTER",
      "city": "Красноярск",
      "image": "/src/components/pages/images/product.jfif",
      "description": "Воздушный фильтр для грузовых автомобилей КАМАЗ.",
      "availability": false
    }
  ],
  "users": [
    {
      "id": "1",
      "email": "akgs@akgs.ru",
      "password": "123456"
    },
    {
      "id": "ebe7",
      "name": "Александра",
      "email": "2723434@mail.ru",
      "password": "123456"
    }
  ]
}